reprotools/__init__.py
reprotools/auto_peds.py
reprotools/diff_file_size.py
reprotools/make_copy.py
reprotools/peds.py
reprotools/subj_clustering.py
reprotools/verify_files.py
reprotools/test/checksums.sh
reprotools/test/conditions.txt
reprotools/test/differences-ref.json
reprotools/test/differences.txt
reprotools/test/exclude_items.txt
reprotools/test/fileDiff_column_index.txt
reprotools/test/fileDiff_differences.txt
reprotools/test/fileDiff_differences_subject_total.txt
reprotools/test/fileDiff_row_index.txt
reprotools/test/matrix.txt
reprotools/test/metrics-list.csv
reprotools/test/metrics.csv
reprotools/test/mock-utility-matrix.txt
reprotools/test/peds_test_datatest.txt
reprotools/test/test_file_size.py
reprotools/test/test_peds.py
reprotools/test/test_verify_files.py
reprotools/test/__pycache__/test_file_size.cpython-27-PYTEST.pyc
reprotools/test/__pycache__/test_peds.cpython-27-PYTEST.pyc
reprotools/test/__pycache__/test_plot_matrix.cpython-27-PYTEST.pyc
reprotools/test/__pycache__/test_verify_files.cpython-27-PYTEST.pyc
reprotools/test/a/a.txt
reprotools/test/b/a.txt
reprotools/test/condition1/subject1/a.txt
reprotools/test/condition1/subject1/b.txt
reprotools/test/condition1/subject1/c/c.txt
reprotools/test/condition1/subject1/c/d.txt
reprotools/test/condition1/subject2/a.txt
reprotools/test/condition1/subject2/b.txt
reprotools/test/condition1/subject2/e.txt
reprotools/test/condition1/subject2/c/c.txt
reprotools/test/condition1/subject2/f/f.txt
reprotools/test/condition2/subject1/a.txt
reprotools/test/condition2/subject1/b.txt
reprotools/test/condition2/subject1/c/c.txt
reprotools/test/condition2/subject2/a.txt
reprotools/test/condition2/subject2/b.txt
reprotools/test/condition2/subject2/e.txt
reprotools/test/condition2/subject2/c/c.txt
reprotools/test/condition2/subject2/f/f.txt
reprotools/test/condition3/subject1/a.txt
reprotools/test/condition3/subject1/b.txt
reprotools/test/condition3/subject1/c/c.txt
reprotools/test/condition3/subject2/a.txt
reprotools-0.0.2.dist-info/LICENSE
reprotools-0.0.2.dist-info/METADATA
reprotools-0.0.2.dist-info/WHEEL
reprotools-0.0.2.dist-info/entry_points.txt
reprotools-0.0.2.dist-info/top_level.txt
reprotools-0.0.2.dist-info/RECORD
